<?xml version="1.0" encoding="UTF-8"?>
<site>
   <feature url="features/mirur.feature_1.1.1.qualifier.jar" id="mirur.feature" version="1.1.1.qualifier" os="linux,macosx,win32" arch="x86,x86_64">
      <category name="mirur.category"/>
   </feature>
   <!--
   <bundle id="mirur.jogl-linux32" version="0.6.0">
      <category name="mirur.category"/>
   </bundle>
   <bundle id="mirur.jogl-linux64" version="0.6.0">
      <category name="mirur.category"/>
   </bundle>
   <bundle id="mirur.jogl-osx" version="0.6.0">
      <category name="mirur.category"/>
   </bundle>
   <bundle id="mirur.jogl-win32" version="0.6.0">
      <category name="mirur.category"/>
   </bundle>
   <bundle id="mirur.jogl-win64" version="0.6.0">
      <category name="mirur.category"/>
   </bundle>
   -->
   <category-def name="mirur.category" label="Mirur Debugging Tool">
      <description>
         Mirur debugging tool
      </description>
   </category-def>
</site>
